{
  "ideas": [
    {
      "index": 0,
      "x": 30.548091866891756,
      "y": -38.9224677695695,
      "id": 1,
      "title": "New Workspace Doors",
      "content": "I think the ugliest part of the Workspace are the glass doors at the entry. I would suggest that we replace them with better looking ones and get rid of the notices posted on them, or redesign them"
    },
    {
      "index": 1,
      "x": 17.22906066949001,
      "y": -38.17351595329304,
      "id": 2,
      "title": "Fire extinguishers",
      "content": "Put a fire extinguisher in each office.",
      "thumbnailPath": "/media/improve-hcc-workspace/icons/7.png"
    },
    {
      "index": 2,
      "x": 29.56840785020109,
      "y": -51.198957834555685,
      "id": 3,
      "title": "Decorate the office doors",
      "content": "Decorate the office doors",
      "thumbnailPath": "/media/improve-hcc-workspace/icons/7.png"
    },
    {
      "index": 3,
      "x": 24.500913464763435,
      "y": -82.27086059054811,
      "id": 4,
      "title": "Open up space",
      "content": "Move the cabinet in front of the printer to the side, get rid of the small table and move the sofa to the wall. Big screen should go in the meeting room or hallway, preferably close to the glass doors.",
      "thumbnailPath": "/media/improve-hcc-workspace/icons/7.png"
    },
    {
      "index": 4,
      "x": 13.17916578874645,
      "y": -60.16796471907287,
      "id": 5,
      "title": "Idea Space",
      "content": "Clear the usability lab, remove its door, make it an idea space/hangout",
      "thumbnailPath": "/media/improve-hcc-workspace/icons/7.png"
    },
    {
      "index": 5,
      "x": -20.905714197855588,
      "y": -11.795401005612895,
      "id": 6,
      "title": "Touchscreen Welcome",
      "content": "Putting the touchscreen in front of workspace visualizing the HCC work",
      "thumbnailPath": "/media/improve-hcc-workspace/icons/7.png"
    },
    {
      "index": 6,
      "x": 10.95745758118691,
      "y": -71.72141371992163,
      "id": 7,
      "title": "re-organization",
      "content": "removing the sofa from the kitchen and put some plants",
      "thumbnailPath": "/media/improve-hcc-workspace/icons/7.png"
    },
    {
      "index": 7,
      "x": -4.862500248896498,
      "y": -16.60696007574919,
      "id": 8,
      "title": "hallway with bouquet",
      "content": "put a small bouquet in front of each office",
      "thumbnailPath": "/media/improve-hcc-workspace/icons/7.png"
    },
    {
      "index": 8,
      "x": -19.488391910743392,
      "y": 0.19591323633364294,
      "id": 9,
      "title": "Keep the sofa",
      "content": "Keep the sofa in the kitchen!!!! Since I could not reply to other ideas, I had to submit a new one.",
      "thumbnailPath": "/media/improve-hcc-workspace/icons/7.png"
    },
    {
      "index": 9,
      "x": -10.81141201725427,
      "y": -66.3000952664438,
      "id": 10,
      "title": "Plants",
      "content": "More plants in the kitchen and maybe at the end of the hallway. Right now only two sad looking plants are in the kitchen.",
      "thumbnailPath": "/media/improve-hcc-workspace/icons/7.png"
    },
    {
      "index": 10,
      "x": -7.492245345579312,
      "y": -55.42972293604794,
      "id": 11,
      "title": "Using the whiteboard",
      "content": "We should put the whiteboard in the hallway to better use... maybe add short news like papers that got accepted or when someone new joins the group",
      "thumbnailPath": "/media/improve-hcc-workspace/icons/7.png"
    },
    {
      "index": 11,
      "x": -25.283392278370222,
      "y": -25.36717958353025,
      "id": 12,
      "title": "Kitchen Notes",
      "content": "In the kitchen are a lot of notes saying what to do and what not to do. Most of them look really old. We should renew them and check which are actually necessary.",
      "thumbnailPath": "/media/improve-hcc-workspace/icons/7.png"
    },
    {
      "index": 12,
      "x": -35.03029079673146,
      "y": 5.5177708155290786,
      "id": 13,
      "title": "Show off our accomplishments in research with wall display",
      "content": "We could show off our accomplishments in research with LED wall display in the hallway.",
      "thumbnailPath": "/media/improve-hcc-workspace/icons/13.png"
    },
    {
      "index": 13,
      "x": -18.288118520107737,
      "y": -49.76178981656172,
      "id": 14,
      "title": "Cleaning stuff",
      "content": "A vacuum cleaner is an important requirement I guess. Staff may need to get rid of dirt that may occur suddenly on the carpet rather than to keep waiting for someone to come and clean.",
      "thumbnailPath": "/media/improve-hcc-workspace/icons/7.png"
    },
    {
      "index": 14,
      "x": -42.38482705738695,
      "y": -21.815913360672344,
      "id": 15,
      "title": "Long collective debate",
      "content": "long vocal discussion in one room may disturb other researchers in other rooms. I suggest that, those who are planning  to go for long vocal discussion to do it in the room located in the middle of the building, in front of the stairs.",
      "thumbnailPath": "/media/improve-hcc-workspace/icons/7.png"
    },
    {
      "index": 15,
      "x": -35.84729458281352,
      "y": -8.219157556802314,
      "id": 16,
      "title": "New floor covering",
      "content": "The carpeted floor could be replaced with some other, more modern floor covering (e.g. screed floor).",
      "thumbnailPath": "/media/improve-hcc-workspace/icons/7.png"
    },
    {
      "index": 16,
      "x": -30.304180392557118,
      "y": -76.71810867414997,
      "id": 17,
      "title": "Kitchen improvement",
      "content": "Kitchen: 1. Clean the kitchen; 2. reorganize the kitchen and move the printer to the usability lab (create a building space, with all printers and other creative stuff); 2. buy new furniture for eating; 4. replace blue coffee machine",
      "thumbnailPath": "/media/improve-hcc-workspace/icons/7.png"
    },
    {
      "index": 17,
      "x": -47.81936383842038,
      "y": -0.6217411337895099,
      "id": 18,
      "title": "Hallway Improvement",
      "content": "Bring different colors on the wall and define spaces for different topics, for example, people space, project space, activity space, paper space, ...",
      "thumbnailPath": "/media/improve-hcc-workspace/icons/7.png"
    },
    {
      "index": 18,
      "x": -39.076098864836375,
      "y": -69.22733010871389,
      "id": 19,
      "title": "Kitchen poster",
      "content": "Put a poster on the wall next to the table. Something inspiring and/or calming with no relation to actual research of the group.",
      "thumbnailPath": "/media/improve-hcc-workspace/icons/7.png"
    },
    {
      "index": 19,
      "x": 21.446011632462447,
      "y": 94.8543899891588,
      "id": 20,
      "title": "Floorplants!",
      "content": "Plants on the floor",
      "thumbnailPath": "/media/improve-hcc-workspace/icons/20.png"
    },
    {
      "index": 20,
      "x": 28.547355563811127,
      "y": 85.009247685594,
      "id": 21,
      "title": "asdfasfd",
      "content": "plants from new material that light-up during a fire",
      "thumbnailPath": "/media/improve-hcc-workspace/icons/21.png"
    },
    {
      "index": 21,
      "x": 38.723948203618725,
      "y": 97.44015620070567,
      "id": 22,
      "title": "Heureka",
      "content": "Heureka! - New idea!",
      "thumbnailPath": null
    },
    {
      "index": 22,
      "x": 34.307744412361146,
      "y": 121.3600322885781,
      "id": 33,
      "title": "asdfasdf",
      "content": "Proceedings of the 2016 CHI Conference Extended Abstracts on Human Factors in Computing Systems",
      "thumbnailPath": null
    },
    {
      "index": 23,
      "x": 43.29293597799553,
      "y": 112.90136887734806,
      "id": 34,
      "title": "asdfasdfs",
      "content": "If the item is a thesis or a dissertation, non-University of Illinois affiliates can request a copy through their local Interlibrary Loan Office",
      "thumbnailPath": "/media/improve-hcc-workspace/icons/34.png"
    },
    {
      "index": 24,
      "x": 17.35959198928503,
      "y": 117.93005779788385,
      "id": 35,
      "title": "asdfs awesome idea thing",
      "content": "plants from new material that light-up during a fire",
      "thumbnailPath": null
    },
    {
      "index": 25,
      "x": 27.933145050739185,
      "y": 109.10964321390344,
      "id": 36,
      "title": "asdfasdfasdf",
      "content": "The importance of iteration in creative conceptual combination",
      "thumbnailPath": "/media/improve-hcc-workspace/icons/36.png"
    }
  ]
}
